{
	"id": "919ca3c3-14d9-4cef-8a44-44aaa5380bc6",
	"values": [
		{
			"key": "timeStamp",
			"value": "2432020101235",
			"enabled": true
		},
		{
			"key": "token",
			"value": "eyJhbGciOiJIUzI1NiIsInR5cCI6IkpXVCJ9.eyJpYXQiOjE1ODQ5NDYzMjY4MDh9.18aC5mn-TAFhJAoJnfzwzD14ioIh3pdSx2EQrk6r-UM",
			"enabled": true
		},
		{
			"key": "timestamp",
			"value": "03/06/2020",
			"enabled": true
		},
		{
			"key": "userid",
			"value": "C_Rd5ykyw",
			"enabled": true
		},
		{
			"key": "organizationid",
			"value": "YzxtQJjr5",
			"enabled": true
		},
		{
			"key": "projectid",
			"value": "kgXyeRJc",
			"enabled": true
		},
		{
			"key": "partnershipid",
			"value": "5dSvB9Sts",
			"enabled": true
		},
		{
			"key": "password",
			"value": "test@123",
			"enabled": true
		},
		{
			"key": "email",
			"value": "2332020061017invalid@mailinator.com",
			"enabled": true
		},
		{
			"key": "languageid",
			"value": "qog2ywN3R",
			"enabled": true
		},
		{
			"key": "productid",
			"value": "Ke2reuK1y",
			"enabled": true
		},
		{
			"key": "internshipEngagementid",
			"value": "6ReFkO-M",
			"enabled": true
		},
		{
			"key": "educationid",
			"value": "zJAJE2ATf",
			"enabled": true
		},
		{
			"key": "budgetid",
			"value": "3owvOilke",
			"enabled": true
		},
		{
			"key": "requestuploadid",
			"value": "tmpUiLso",
			"enabled": true
		},
		{
			"key": "fileid",
			"value": "770BjkEd",
			"enabled": true
		},
		{
			"key": "zoneid",
			"value": "pvdDqF-oB",
			"enabled": true
		},
		{
			"key": "unavailabilityid",
			"value": "zcrRcPw-a",
			"enabled": true
		}
	],
	"name": "My Workspace Globals",
	"_postman_variable_scope": "globals",
	"_postman_exported_at": "2020-03-24T05:32:59.541Z",
	"_postman_exported_using": "Postman/7.21.0"
}